stricto/__init__.py
stricto/bool.py
stricto/dict.py
stricto/error.py
stricto/extend.py
stricto/float.py
stricto/generic.py
stricto/in_type.py
stricto/int.py
stricto/json_encoder.py
stricto/list.py
stricto/list_and_tuple.py
stricto/rights.py
stricto/string.py
stricto/tuple.py
stricto/extended/bytes.py
stricto/extended/complex.py
stricto/extended/date_time.py
stricto-0.0.6.dist-info/METADATA
stricto-0.0.6.dist-info/WHEEL
stricto-0.0.6.dist-info/licenses/LICENSE
stricto-0.0.6.dist-info/RECORD
