Metadata-Version: 2.4
Name: stricto
Version: 0.0.6
Summary: Strict Dict (json) with schema validation embedded
Project-URL: GitHub, https://github.com/bwallrich/stricto
Project-URL: Homepage, https://github.com/bwallrich/stricto
Project-URL: Issues, https://github.com/bwallrich/stricto/issues
Author-email: Bertrand Wallrich <Bertrand.Wallrich@inria.fr>
License: MIT License
License-File: LICENSE
Classifier: License :: OSI Approved :: MIT License
Classifier: Operating System :: OS Independent
Classifier: Programming Language :: Python :: 3
Requires-Python: >=3.8
